mapreduce-0.3.4.data/scripts/mr_draw_invocation_graph
mapreduce-0.3.4.data/scripts/mr_get_invocation_flat_list
mapreduce-0.3.4.data/scripts/mr_get_invocation_graph
mapreduce-0.3.4.data/scripts/mr_get_request_sessions
mapreduce-0.3.4.data/scripts/mr_http_notification_listen
mapreduce-0.3.4.data/scripts/mr_kv_handler_create
mapreduce-0.3.4.data/scripts/mr_kv_handler_delete
mapreduce-0.3.4.data/scripts/mr_kv_handler_get
mapreduce-0.3.4.data/scripts/mr_kv_handler_list
mapreduce-0.3.4.data/scripts/mr_kv_handler_store
mapreduce-0.3.4.data/scripts/mr_kv_invocation_create
mapreduce-0.3.4.data/scripts/mr_kv_invocation_get
mapreduce-0.3.4.data/scripts/mr_kv_job_create
mapreduce-0.3.4.data/scripts/mr_kv_job_delete
mapreduce-0.3.4.data/scripts/mr_kv_job_get
mapreduce-0.3.4.data/scripts/mr_kv_job_list
mapreduce-0.3.4.data/scripts/mr_kv_request_cleanup
mapreduce-0.3.4.data/scripts/mr_kv_request_create
mapreduce-0.3.4.data/scripts/mr_kv_request_get
mapreduce-0.3.4.data/scripts/mr_kv_step_create
mapreduce-0.3.4.data/scripts/mr_kv_step_delete
mapreduce-0.3.4.data/scripts/mr_kv_step_get
mapreduce-0.3.4.data/scripts/mr_kv_step_list
mapreduce-0.3.4.data/scripts/mr_kv_step_set_handler
mapreduce-0.3.4.data/scripts/mr_kv_step_update_handlers
mapreduce-0.3.4.data/scripts/mr_kv_t_mapped_steps_add
mapreduce-0.3.4.data/scripts/mr_kv_t_mapped_steps_create.obs
mapreduce-0.3.4.data/scripts/mr_kv_t_mapped_steps_get.obs
mapreduce-0.3.4.data/scripts/mr_kv_workflow_create
mapreduce-0.3.4.data/scripts/mr_kv_workflow_delete
mapreduce-0.3.4.data/scripts/mr_kv_workflow_get
mapreduce-0.3.4.data/scripts/mr_start_gunicorn_dev
mapreduce-0.3.4.data/scripts/mr_start_gunicorn_prod
mapreduce-0.3.4.dist-info/DESCRIPTION.rst
mapreduce-0.3.4.dist-info/METADATA
mapreduce-0.3.4.dist-info/metadata.json
mapreduce-0.3.4.dist-info/RECORD
mapreduce-0.3.4.dist-info/top_level.txt
mapreduce-0.3.4.dist-info/WHEEL
mr/__init__.py
mr/compat.py
mr/constants.py
mr/email_support.py
mr/job_engine.py
mr/log.py
mr/request_cleanup.py
mr/shared_types.py
mr/trace.py
mr/utility.py
mr/workflow_manager.py
mr/app/__init__.py
mr/app/main.py
mr/cache/__init__.py
mr/cache/cache.py
mr/cache/redis.py
