Metadata-Version: 2.0
Name: mapreduce
Version: 0.3.4
Summary: A Python-based, distributed MapReduce solution.
Home-page: https://github.com/dsoprea/JobX
Author: Dustin Oprea
Author-email: myselfasunder@gmail.com
License: GPL 2
Keywords: mapreduce jobx jobs workers
Platform: UNKNOWN
Requires-Dist: Flask (==0.10.1)
Requires-Dist: Jinja2 (==2.7.3)
Requires-Dist: MarkupSafe (==0.23)
Requires-Dist: Werkzeug (==0.9.6)
Requires-Dist: etcd
Requires-Dist: fs (==0.5.0)
Requires-Dist: gevent (==1.0.1)
Requires-Dist: graphviz (==0.4)
Requires-Dist: greenlet (==0.4.2)
Requires-Dist: gunicorn (==19.1.1)
Requires-Dist: itsdangerous (==0.24)
Requires-Dist: nsqs (==0.2.0)
Requires-Dist: pytz (==2013.8)
Requires-Dist: redis (==2.10.3)
Requires-Dist: requests (==2.1.0)
Requires-Dist: six (==1.8.0)
Requires-Dist: wsgiref (==0.1.2)
Requires-Dist: markdown
